period_tracker/__init__.py
period_tracker/__main__.py
period_tracker/config.py
period_tracker/crypto.py
period_tracker/data.py
period_tracker/logic.py
period_tracker/gui/__init__.py
period_tracker/gui/calendar_view.py
period_tracker/gui/entry_controls.py
period_tracker/gui/layout.py
period_tracker/gui/summary.py
period_tracker-0.1.1.dist-info/licenses/LICENSE
period_tracker-0.1.1.dist-info/METADATA
period_tracker-0.1.1.dist-info/WHEEL
period_tracker-0.1.1.dist-info/entry_points.txt
period_tracker-0.1.1.dist-info/top_level.txt
period_tracker-0.1.1.dist-info/RECORD
