Metadata-Version: 2.4
Name: period-tracker
Version: 0.1.1
Author-email: Daniel Taylor <kingorgg@gmail.com>
License-Expression: MIT
Project-URL: Repository, https://codeberg.org/kingorgg/period_tracker.git
Project-URL: Issues, https://codeberg.org/kingorgg/period_tracker/issues
Classifier: Programming Language :: Python :: 3
Classifier: Operating System :: OS Independent
License-File: LICENSE
Requires-Dist: tkcalendar
Requires-Dist: matplotlib
Provides-Extra: dev
Requires-Dist: black; extra == "dev"
Requires-Dist: pytest; extra == "dev"
Dynamic: license-file
